LICENSE
README.md
pyproject.toml
setup.cfg
src/poindexter/models/APIKey.py
src/poindexter/models/CSE.py
src/poindexter/models/CSECX.py
src/poindexter/models/Domain.py
src/poindexter/models/Job.py
src/poindexter/models/Keyword.py
src/poindexter/models/Link.py
src/poindexter/models/Plugin.py
src/poindexter/models/PluginOutput.py
src/poindexter/models/Profile.py
src/poindexter/models/ProfileTemplate.py
src/poindexter/models/Report.py
src/poindexter/models/Tag.py
src/poindexter/models/__init__.py
src/poindexter_models.egg-info/PKG-INFO
src/poindexter_models.egg-info/SOURCES.txt
src/poindexter_models.egg-info/dependency_links.txt
src/poindexter_models.egg-info/not-zip-safe
src/poindexter_models.egg-info/requires.txt
src/poindexter_models.egg-info/top_level.txt