Metadata-Version: 2.1
Name: poindexter-models
Version: 0.0.14
Summary: enhanced Google dorking (data model)
Home-page: UNKNOWN
Author: Peter Crampton
License: MIT
Platform: unix
Platform: linux
Requires-Python: >=3.6
License-File: LICENSE
